immrax/__init__.py
immrax/control.py
immrax/embedding.py
immrax/neural.py
immrax/utils.py
immrax/_vendor/__init__.py
immrax/_vendor/jax_verify/.git
immrax/_vendor/jax_verify/.gitignore
immrax/_vendor/jax_verify/.travis.yml
immrax/_vendor/jax_verify/CONTRIBUTING.md
immrax/_vendor/jax_verify/LICENSE
immrax/_vendor/jax_verify/README.md
immrax/_vendor/jax_verify/requirements.txt
immrax/_vendor/jax_verify/setup.py
immrax/_vendor/jax_verify/docs/Makefile
immrax/_vendor/jax_verify/docs/api.rst
immrax/_vendor/jax_verify/docs/conf.py
immrax/_vendor/jax_verify/docs/index.rst
immrax/_vendor/jax_verify/docs/requirements.txt
immrax/_vendor/jax_verify/docs/sdp_verify.rst
immrax/_vendor/jax_verify/examples/run_boundprop.py
immrax/_vendor/jax_verify/examples/run_examples.sh
immrax/_vendor/jax_verify/examples/run_lp_solver.py
immrax/_vendor/jax_verify/examples/run_sdp_verify.py
immrax/_vendor/jax_verify/jax_verify/__init__.py
immrax/_vendor/jax_verify/jax_verify/sdp_verify.py
immrax/_vendor/jax_verify/jax_verify/extensions/functional_lagrangian/README.md
immrax/_vendor/jax_verify/jax_verify/extensions/functional_lagrangian/attacks.py
immrax/_vendor/jax_verify/jax_verify/extensions/functional_lagrangian/bounding.py
immrax/_vendor/jax_verify/jax_verify/extensions/functional_lagrangian/data.py
immrax/_vendor/jax_verify/jax_verify/extensions/functional_lagrangian/dual_build.py
immrax/_vendor/jax_verify/jax_verify/extensions/functional_lagrangian/dual_solve.py
immrax/_vendor/jax_verify/jax_verify/extensions/functional_lagrangian/lagrangian_form.py
immrax/_vendor/jax_verify/jax_verify/extensions/functional_lagrangian/model.py
immrax/_vendor/jax_verify/jax_verify/extensions/functional_lagrangian/specification.py
immrax/_vendor/jax_verify/jax_verify/extensions/functional_lagrangian/verify_utils.py
immrax/_vendor/jax_verify/jax_verify/extensions/functional_lagrangian/inner_solvers/__init__.py
immrax-0.3.4.dist-info/METADATA
immrax-0.3.4.dist-info/WHEEL
immrax-0.3.4.dist-info/RECORD
