Metadata-Version: 2.4
Name: immrax
Version: 0.3.4
Project-URL: Homepage, https://github.com/gtfactslab/immrax
Project-URL: Documentation, https://immrax.readthedocs.io
Project-URL: Bug Tracker, https://github.com/gtfactslab/immrax/issues
Project-URL: Source Code, https://github.com/gtfactslab/immrax
Requires-Dist: absl-py
Requires-Dist: cvxpy
Requires-Dist: diffrax~=0.7.0
Requires-Dist: dm-haiku
Requires-Dist: dm-tree
Requires-Dist: einshape
Requires-Dist: equinox~=0.12.2
Requires-Dist: immutabledict~=4.2.0
Requires-Dist: jaxtyping~=0.2.33
Requires-Dist: jax~=0.6.1
Requires-Dist: linrax~=0.1.0
Requires-Dist: matplotlib~=3.9.2
Requires-Dist: ml-collections
Requires-Dist: numpy~=2.3.2
Requires-Dist: optax
Requires-Dist: pypoman~=1.1.0
Requires-Dist: scipy~=1.16.1
Requires-Dist: shapely~=2.0.6
Requires-Dist: tabulate~=0.9.0
Provides-Extra: cuda
Requires-Dist: jax[cuda12]~=0.6.1; extra == 'cuda'
Requires-Dist: linrax[cuda]; extra == 'cuda'
Provides-Extra: examples
Requires-Dist: casadi~=3.6.7; extra == 'examples'
Requires-Dist: control~=0.10.1; extra == 'examples'
Requires-Dist: ipykernel~=6.29.5; extra == 'examples'
Requires-Dist: ipympl~=0.9.7; extra == 'examples'
